setup.py
yandex_pdd/__init__.py
yandex_pdd/yandex_pdd.py
yandex_pdd.egg-info/PKG-INFO
yandex_pdd.egg-info/SOURCES.txt
yandex_pdd.egg-info/dependency_links.txt
yandex_pdd.egg-info/not-zip-safe
yandex_pdd.egg-info/requires.txt
yandex_pdd.egg-info/top_level.txt