Metadata-Version: 1.0
Name: yandex-pdd
Version: 0.12b0
Summary: API Yandex PDD
Home-page: http://github.com/zt50tz/yandex-pdd
Author: Alexeev Nick
Author-email: n@akolka.ru
License: MIT
Platform: UNKNOWN
